kr_translator/__init__.py
kr_translator/caller.py
kr_translator/exceptions.py
kr_translator-0.1.7.dist-info/LICENSE.md
kr_translator-0.1.7.dist-info/METADATA
kr_translator-0.1.7.dist-info/WHEEL
kr_translator-0.1.7.dist-info/RECORD
