Metadata-Version: 2.3
Name: kr-translator
Version: 0.1.7
Summary: Translate korean text
License: MIT
Author: zlood
Requires-Python: >=3.12,<4.0
Classifier: License :: OSI Approved :: MIT License
Classifier: Operating System :: OS Independent
Classifier: Programming Language :: Python :: 3
Classifier: Programming Language :: Python :: 3.12
Classifier: Programming Language :: Python :: 3.13
Requires-Dist: langchain (>=0.3.4,<0.4.0)
Requires-Dist: langchain-community (>=0.3.1,<0.4.0)
Requires-Dist: langchain-google-genai (>=2.0.1,<3.0.0)
Requires-Dist: langchain-huggingface (>=0.1.0,<0.2.0)
Requires-Dist: langchain-openai (>=0.2.3,<0.3.0)
Requires-Dist: langsmith (>=0.1.136,<0.2.0)
Requires-Dist: protobuf (>=5.27.3,<6.0.0)
Requires-Dist: sentencepiece (>=0.2.0,<0.3.0)
Requires-Dist: transformers (>=4.49.0,<5.0.0)
